README.md
setup.cfg
setup.py
atp/__init__.py
atp/api.py
x_atp_api.egg-info/PKG-INFO
x_atp_api.egg-info/SOURCES.txt
x_atp_api.egg-info/dependency_links.txt
x_atp_api.egg-info/entry_points.txt
x_atp_api.egg-info/requires.txt
x_atp_api.egg-info/top_level.txt